{
  "uuid": "149cd021-74fa-49ab-b2a3-f2a1511203e4",
  "name": "top",
  "description": "",
  "extraSearchTerms": [
    "bm"
  ],
  "tags": [
    "bm"
  ],
  "code": "\tpublic static void main(String[] args)\r\n\t\t\tthrows IOException, SAXException, ParserConfigurationException, XPathExpressionException {\r\n\t\t// Create an AlchemyAPI object.\r\n\r\n\t\tAlchemyAPI alchemyObj \u003d AlchemyAPI.GetInstanceFromString(\"5fc91e98eacfa5ebf83440e8c6a61d0f60fa380b\");\r\n\t\tString URLString \u003d \"http://www.politico.com/\";\r\n\t\tSystem.out.println(\"URL sent to URLGetText AlchemyAPI --\u003e \" + URLString);\r\n\r\n\t\tDocument doc \u003d alchemyObj.URLGetText(URLString);\r\n\t\tString convertDocToString \u003d AlchemyUtility.getStringFromDocument(doc);\r\n\t\tString alchemyAPIResult \u003d AlchemyUtility.returnResultFromXML(convertDocToString, \"text\");\r\n\t\t// System.out.println(convertDocToString);\r\n\t\tSystem.out.println(\"Output from URLGetText AlchemyAPI: Extracted Text is --\u003e \" + alchemyAPIResult);\r\n\r\n\t}",
  "location": "JAVA",
  "dependencies": [
    {
      "groupId": "ch.qos.logback",
      "artifactId": "logback-classic",
      "version": "0.0.0"
    }
  ]
}